pyloghub/__init__.py
pyloghub/advanced_center_of_gravity.py
pyloghub/center_of_gravity.py
pyloghub/center_of_gravity_plus.py
pyloghub/dataset.py
pyloghub/demand_forecasting.py
pyloghub/distance_calculation.py
pyloghub/distance_calculation_with_extra_details.py
pyloghub/fixed_center_of_gravity.py
pyloghub/freight_matrix.py
pyloghub/freight_matrix_plus.py
pyloghub/freight_shipment_emissions_air.py
pyloghub/freight_shipment_emissions_rail.py
pyloghub/freight_shipment_emissions_road.py
pyloghub/freight_shipment_emissions_sea.py
pyloghub/geocoding.py
pyloghub/input_data_validation.py
pyloghub/isochrone.py
pyloghub/isochrone_plus.py
pyloghub/location_planning.py
pyloghub/milkrun_optimization.py
pyloghub/milkrun_optimization_plus.py
pyloghub/nearest_warehouses.py
pyloghub/network_design_plus.py
pyloghub/save_to_platform.py
pyloghub/sending_requests.py
pyloghub/shipment_analyzer.py
pyloghub/supply_chain_map_areas.py
pyloghub/supply_chain_map_locations.py
pyloghub/supply_chain_map_polyline.py
pyloghub/supply_chain_map_relations.py
pyloghub/supply_chain_map_routes.py
pyloghub/supply_chain_map_sea_routes.py
pyloghub/transport_optimization.py
pyloghub/transport_optimization_plus.py
pyloghub/sample_data/AdvancedCoGAddresses.xlsx
pyloghub/sample_data/AdvancedCoGReverse.xlsx
pyloghub/sample_data/CO2Air.xlsx
pyloghub/sample_data/CO2RailAddresses.xlsx
pyloghub/sample_data/CO2RailReverse.xlsx
pyloghub/sample_data/CO2RoadAddresses.xlsx
pyloghub/sample_data/CO2RoadReverse.xlsx
pyloghub/sample_data/CO2Sea.xlsx
pyloghub/sample_data/COGPlusSampleDataAddresses.xlsx
pyloghub/sample_data/COGPlusSampleDataReverse.xlsx
pyloghub/sample_data/COGSampleDataAddresses.xlsx
pyloghub/sample_data/COGSampleDataReverse.xlsx
pyloghub/sample_data/DistanceCalcSampleDataAddresses.xlsx
pyloghub/sample_data/DistanceCalcSampleDataReverse.xlsx
pyloghub/sample_data/DistanceCalculationReverse.xlsx
pyloghub/sample_data/FixedCOGSampleDataAddresses.xlsx
pyloghub/sample_data/FixedCOGSampleDataReverse.xlsx
pyloghub-0.1.6.dist-info/licenses/LICENSE
pyloghub-0.1.6.dist-info/METADATA
pyloghub-0.1.6.dist-info/WHEEL
pyloghub-0.1.6.dist-info/top_level.txt
pyloghub-0.1.6.dist-info/RECORD
