Metadata-Version: 2.4
Name: pyloghub
Version: 0.1.6
Summary: The `pyloghub` package provides convinient access to various Log-hub API services for Supply Chain Visualization, Network Design Optimization, and Transport Optimization as well as access to the Log-hub platform data.
Home-page: https://github.com/log-hub/log-hub-python
Author: Log-hub AG
Author-email: support@log-hub.com
License: MIT
Classifier: Programming Language :: Python :: 3
Classifier: License :: OSI Approved :: MIT License
Classifier: Operating System :: OS Independent
License-File: LICENSE
Requires-Dist: requests
Requires-Dist: numpy
Requires-Dist: pandas
Requires-Dist: openpyxl
Requires-Dist: python-dotenv
Dynamic: author
Dynamic: author-email
Dynamic: classifier
Dynamic: description
Dynamic: description-content-type
Dynamic: home-page
Dynamic: license
Dynamic: license-file
Dynamic: requires-dist
Dynamic: summary
